_custom_build.py
kstar_planner/__version__.py
kstar_planner/__main__.py
kstar_planner/__init__.py
kstar_planner/planners.py
kstar_planner/builds/release/bin/preprocess
kstar_planner/builds/release/bin/downward
kstar_planner/builds/release/bin/translate/graph.py
kstar_planner/builds/release/bin/translate/simplify.py
kstar_planner/builds/release/bin/translate/instantiate.py
kstar_planner/builds/release/bin/translate/normalize.py
kstar_planner/builds/release/bin/translate/translate.py
kstar_planner/builds/release/bin/translate/invariant_finder.py
kstar_planner/builds/release/bin/translate/build_model.py
kstar_planner/builds/release/bin/translate/invariants.py
kstar_planner/builds/release/bin/translate/sas_tasks.py
kstar_planner/builds/release/bin/translate/pddl_to_prolog.py
kstar_planner/builds/release/bin/translate/greedy_join.py
kstar_planner/builds/release/bin/translate/options.py
kstar_planner/builds/release/bin/translate/variable_order.py
kstar_planner/builds/release/bin/translate/fact_groups.py
kstar_planner/builds/release/bin/translate/split_rules.py
kstar_planner/builds/release/bin/translate/sccs.py
kstar_planner/builds/release/bin/translate/axiom_rules.py
kstar_planner/builds/release/bin/translate/timers.py
kstar_planner/builds/release/bin/translate/constraints.py
kstar_planner/builds/release/bin/translate/tools.py
kstar_planner/builds/release/bin/translate/pddl/f_expression.py
kstar_planner/builds/release/bin/translate/pddl/pddl_types.py
kstar_planner/builds/release/bin/translate/pddl/tasks.py
kstar_planner/builds/release/bin/translate/pddl/functions.py
kstar_planner/builds/release/bin/translate/pddl/axioms.py
kstar_planner/builds/release/bin/translate/pddl/effects.py
kstar_planner/builds/release/bin/translate/pddl/conditions.py
kstar_planner/builds/release/bin/translate/pddl/actions.py
kstar_planner/builds/release/bin/translate/pddl/predicates.py
kstar_planner/builds/release/bin/translate/pddl/__init__.py
kstar_planner-1.4.16.dist-info/WHEEL
kstar_planner-1.4.16.dist-info/entry_points.txt
kstar_planner-1.4.16.dist-info/top_level.txt
kstar_planner-1.4.16.dist-info/METADATA
kstar_planner-1.4.16.dist-info/RECORD
kstar_planner-1.4.16.dist-info/licenses/LICENSE
kstar_planner-1.4.16.dist-info/licenses/LICENSE.md
