Metadata-Version: 2.4
Name: kstar-planner
Version: 1.4.16
Summary: Kstar Planner is an Automated PDDL based planner that includes planners for top-k and top-quality planning computational tasks.
Author-email: "Michael Katz, Junkyu Lee" <michael.katz1@ibm.com>
License:                     GNU GENERAL PUBLIC LICENSE
Project-URL: Homepage, https://github.com/IBM/kstar
Keywords: planning
Classifier: License :: OSI Approved :: GNU General Public License v3 (GPLv3)
Requires-Python: >=3.8
License-File: LICENSE
License-File: LICENSE.md
Dynamic: license-file
